[
  {
    "section_id": "executive_summary",
    "title": "Executive Summary",
    "digest": "[PDF pages 16-19]\n2 | TIMOR-LESTE NATIONAL HUMAN DEVELOPMENT REPORT 2018 A larger share of men experience well-being deprivations, at 11 percent compared with 9 percent among women. A majority of young men and women, around 88 percent, experience deprivations in education. Among the survey respondents, 82 percent (87 percent of women and 77 percent of men) did not have jobs, and only 46 percent were studying or undergoing training at the time of the survey (44 percent of women and 49 percent of men), suggesting that a large share of youth are idle. Through multisectoral investments and pro - gressive policies in health care, education and the economy, Timor-Leste can be projected to achieve large human development gains and a high human development index of 0.88 by 2050, a level that is enjoyed by the 20 countries with the highest human develop - ment scores in the world today. • Increases in the mean and expected years of schooling among both men and women to 10 and 17 years, respectively, by 2050, thereby removing the gender gap in education The private sector is in the early stages of development and provides employment to only 5 percent of the workforce. According to the 2015 census, the youth unemployment rate in urban areas peaked at 26 percent.\n\n[PDF pages 19-21]\n6 | TIMOR-LESTE NATIONAL HUMAN DEVELOPMENT REPORT 2018 job-seekers and the economically inactive into entrepreneurs, especially among the 62 percent of the population currently below age 25. Some youth already possess work-ready skills through participation in donor-supported, work-ready training programmes or migrant work in more competitive environments overseas. This will enable more young people to gain the skills, confidence and pride they require to embark on social enterprise development that will assist their communities in exiting from poverty. National HDR suggests that the Government draw on international best practice and con - sider allocating 25 percent of the budget to education and training to ensure access to quality education among young women and men. Experience elsewhere shows that raising school completion rates up to grade 12 can become a major factor in reducing youth unemployment. This National HDR suggests that the gender gap in education should be addressed through a comprehen - sive approach aimed at eliminating all school fees, providing training and creating employ - ment for sufficient numbers of teachers, and extending the coverage of school feeding programmes into secondary schools through grade 12. Through inclusive education pol - icies and practices, a nurturing schooling environment that responds to the diversity of student needs must be ensured to create a learning environment that makes youth feel safe and motivated. This can be achieved through supplementary work placements or non-formal education to engage youth in the solidarity economy before they leave school."
  },
  {
    "section_id": "chapter_1",
    "title": "Planning the Opportunities for Youth",
    "digest": "[PDF pages 23-27]\nTimor-Leste has built a more inclusive political environment since 2006 and expanded tangible public services among the people. It was followed by the second National HDR, The Path Out of Poverty: Integrated Rural Development, launched in 2006, and the third National The economy is supported largely by oil revenues; the Petroleum Fund of Timor-Leste was valued at $16.2 billion at the end of 2015 (IMF 2016). Employment Strategy 2017–2030 empha - sizes that “productive employment is the basis for improving household livelihoods and [the] prosperity of the country as a whole, where equal participation of men and women will be the only way of achieving in - clusive economic growth and social develop - ment” (NES Secretariat 2017, p. A gen - eration-wide window of opportunity will soon open, or has already opened gauged by the economic support ratio (Lee 2017), leading to the possibility of achieving accelerated economic growth and human development gains that may help realize the nation’s development aspirations. However, to achieve the demographic dividend, any favourable changes in the age structure must be accompanied by judicious policies in education and training, health care, infrastructure development and produc - tive employment creation with particular attention to the subgroups of youth lagging furthest behind. A generation-wide window of opportunity will soon open, or has already opened gauged by the economic support ratio (Lee 2017), leading to the possibility of achieving accelerated economic growth and human development gains that may help realize the nation’s development aspirations. SDG 8, to promote sustained, inclusive and sustainable economic growth, full and productive employment and decent work for all.\n\n[PDF pages 27-31]\nOn the transformation of the workplace, the recommendations of this National HDR align with SDG 8, to promote sustained, inclusive and sustainable economic growth, full and productive employment and de - cent work for all. 4 Another SDG 8 target is equally influential in the analytical framework of this National HDR, namely, to adopt policies that support productive activities, decent job creation, entrepreneurship, cre - ativity and innovation and encourage the establishment and expansion of microen - terprises and small and medium enterprises (SMEs), including through access to finan - cial services. The effort would be operational - ized within the framework of SDGs 2 and 3, respectively, to end hunger, achieve food se - curity and improved nutrition and promote sustainable agriculture and to ensure healthy lives and promote well-being for all at all ages.6 As a tool for achieving these SDGs, so - cial entrepreneurship has a distinctive ability to blend social and economic objectives to respond to the multidimensional nature of poverty. Poorly developed adult training and skilling systems in most economies delay the speed of adjustment to the new context by failing to prepare youth, thereby exacer - bating skills gaps and unemployment in the current and future workforce. Relevant recommendations are put forward within the framework of SDG 5, achieving gender equality, social inclu - sion and human rights for all, with explicit targets on ending discrimination and reducing relative deprivations in well-being and other inequalities. The lack of access to secondary education and to sexual and reproductive health services among girls and women is a key driver of gender inequality. Chapter 4 explores the ways educational initiatives and policies may inspire and prepare young people to gain the skills and training necessary for sustainable livelihoods that can contribute to communities. 16 | TIMOR-LESTE NATIONAL HUMAN DEVELOPMENT REPORT 2018 PLANNING THE OPPORTUNITIES FOR A YOUTHFUL POPULATION | 17 1Planning the Opportunities for Youth the knowledge production process among individuals, social enterprises play an essen - tial role as a conduit for skills.\n\n[PDF pages 30-31]\nData are presented that highlight the extent of national ICT coverage, access and use, and the analysis addresses issues revolv - ing around the digital divide that constrain public access to information and the abil - ity to benefit from social networking. The chapter shows that ICT s have buttressed the social enterprise sector in Timor-Leste and provides comparative examples of successful initiatives in other contexts. The chapter considers the types of national training programmes, some of which are ICT based, that may offer future social entrepreneurs adequate skills to develop, promote and extend a social enterprise. Chapter 6 surveys important consider - ations on public investment in education and training initiatives aimed at developing social enterprises among youth in Timor- It investigates appropriate ways through which the Petroleum Fund of Timor-Leste might be used for public investment in youth, including in the incu - bation of social enterprises. It argues that public investment in these initiatives as a crucial means of bridging the financial gap in access that prevents the launch of SMEs, particularly among rural youth and their communities."
  },
  {
    "section_id": "chapter_2",
    "title": "Youth Well-Being and the Demographic Dividend",
    "digest": "[PDF pages 33-38]\nA major factor in the high population growth rates has been the remarkably high total fertility rate among women, especially during the first 10 years since independence (Saikia and Hosgelen 2010). The population age structure is particularly important for economic and human development because it determines the dependency ratio, that is, the ratio of the non-working popula - tion, typically ages 0–14 and 65 or above, to the working population, ages 15–64, and, thus, the prospects for a demographic window of opportunity and a demographic dividend. Productivity increases may occur because of less population pressure on the educational and health care systems, facilitating qualitative and quan - titative improvements in these sectors and leading to the accumulation of human capital and higher productivity (Mason 2003). The Government aspires for the country to reach upper-middle-income status, with a healthy, well-educated and prosperous population, by 2030 (Planning Commission 2011). The gross national income of upper-middle-income countries today is be - tween $3,956 and $12,235; life expectancy at birth is around 75 years; the total fertility rate is near 2.0, and the mean years of schooling is up to 10 years.9 Policy scenario 1 (economy only): This scenario assumes there will be changes only in economic policies and investments. According to this sce - nario, economic improvements are coupled with increases in the mean and expected years of schooling among men and women of at least five years by 2050, that is, to 10 and 17 years, respectively. According to the combined policy scenario (policy scenario 3), improvements in the economy, education and family planning would lead to a minimum replacement fertil - ity rate of 2.1 children per woman by 2048.\n\n[PDF pages 37-44]\nEducation is important for many reasons, including the economic empowerment and better health and well-being it promotes (box 2.1). Studies show investments in greater literacy and in education represent one of the best strategies for reducing under-5 mortality and the birth rate, which is key to a successful de - mographic transition. However, the mean years of schooling among young men and women, 4.2 years, must be raised appreciably. The projected outcomes of the various pol - icy scenarios reveal that the most significant advances in saving the lives of women and children are achieved through investments in family planning (table 2.2). Combining educational and family plan - ning investments promotes the greatest re - duction in the infant, under-5 and maternal mortality rates. The global competitiveness index evaluates 12 components or pillars of com - petitiveness: institutions, infrastructure, the macroeconomic environment, health and primary education, higher education and training, goods market efficiency, labour market efficiency, financial market development, technological readiness, market size, business sophistication, and innovation. The progress projected in education, health and income would also foster substantial improvement in the country’s human devel - opment index (HDI) by 2030 (figure 2.10). Enabling more young women and men to stay in school longer (especially girls in secondary education), expanding equitable access to health care and economic opportunity and enhancing the macroeconomic environment require significant investments that will translate into dividends for future generations.\n\n[PDF pages 43-47]\navailability of a youthful population that is not only vigorous and skilled, but also that is characterized by substantial overall well-be - ing, including physical and mental health, environmental and social awareness and commitment and a willingness to participate in the development process of the nation. Plan 2011–2030 acknowledges that young people are future leaders and that they will eventually be responsible for the social and economic transformation of society (Planning Contemporary measures of the success of development policy focus on the reduction of income poverty, illiteracy, and mortality and morbidity and on promoting long and healthy lives. 30 | TIMOR-LESTE NATIONAL HUMAN DEVELOPMENT REPORT 2018 PLANNING THE OPPORTUNITIES FOR A YOUTHFUL POPULATION | 31 2CHAPTERYouth Well-Being and the Demographic Dividend For example, living standards should not be separated from other aspects of life such as physical and emotional health, governance, community vitality, cul - tural diversity, or environmental resilience. A job might similarly promote improvements in the over - all well-being of an individual or a community by advancing physical and emotional health, facilitating efforts to reach social and environmental goals and fostering community ties. The mix of variables reflects a recognition that well-being is supported by multiple, interconnected and complementary factors, as in the case of models of multidimensional poverty (Alkire and Foster 2011). Education Literacy, formal educational attainment, skills attained through formal and non-formal training, core civic values, ability to manage finances, use of basic ICTs, knowledge of the value of caring for one’s hygiene, nutrition and health, confidence in public speaking\n\n[PDF pages 47-51]\nThe law on the elections of community leaders, for instance, defines young women and young men as individuals ages 17–35, and the Y outh The sampling for the survey has been real - ized in accordance with the share of young women and young men in the 15–34 age group in district, subdistrict and village ad - ministrative units. The final sample covers responses from 420 young men and 391 young women in all 13 districts, 58 of the 65 subdistricts and 97 of the 452 villages. Analysis of disaggregated well-being among youth by age, sex and location reveals that more women than men, more rural residents than urban residents, and more older youth (ages 25–34) than younger youth (ages 15– 24) achieve sufficiency in overall well-being (table 2.6). Although percentage differences are not large, at a maximum of 5 percent - age points, young urban men ages 15–24 require the greater attention of well-being interventions. 36 | TIMOR-LESTE NATIONAL HUMAN DEVELOPMENT REPORT 2018 PLANNING THE OPPORTUNITIES FOR A YOUTHFUL POPULATION | 37 2CHAPTERYouth Well-Being and the Demographic Dividend flooding and a lack of access to clean water are major environmental issues in Timor-Leste, and around 60 percent believe deforestation, slash-and-burn farming and land and air pol - lution are also issues. More than 80 percent of youth know about tara bandu , traditional practices with practical outcomes in environmental protection in Timor-Leste, such as ritual in - vocations of spirits to protect a river that are accompanied by periodic bans on most fishing activities. However, less than half of youth, around 40 percent, have participated in an environmental protection activity.\n\n[PDF pages 51-55]\nThe most well known public programmes among youth include the $3-a-day temporary employment scheme of the Secretaria de Estado para a Politica da Formação Professional e Emprego (Secretariat of State for V ocational T raining Only 50 percent of youth believe they have equal access to employment opportunities in the public sector, and, in access to government services, 10 percent believe they are discriminated against. Indeed, employment opportunities currently available to youth are extremely limited given the approximately 20,000 new entrants into the labour market each year. Between 55 percent and 60 percent of youth have some level of confidence in gov - ernment to listen to them and address their problems by, for instance, creating more jobs or investing in training opportunities. The high dependency ratios may also discourage many young people from working or actively seeking employment given the monthly minimum wage of $115. 40 | TIMOR-LESTE NATIONAL HUMAN DEVELOPMENT REPORT 2018 percent is that their economic outlook will improve in the next two years. Basic education is the highest level of educational attainment among 45 percent of respondents. Many youth also drew a link between unemployment and crime, stating that, if young people have nothing to do, if, for instance, they are not in education, employment, or training (NEET), they may become tempted to carry out socially undesirable activities, such as using drugs or creating conflict.\n\n[PDF pages 55-59]\nThe incidence of deprivation is slightly greater among urban youth in the 15–24 age group. Among youth, 12 percent are deprived in urban areas, but only 8 percent in rural areas. Similarly, 9 percent of young women and 11 percent of young men are deprived. The survey results among deprived youth show that most of them have done relatively well in the physical health and environ - ment domains (table 2.7). The GDI for the general popu - lation in 2015 was 0.905, which means that the women of Timor-Leste measure up to men in human development quite closely though not entirely (a gap of a little less than 10 percent). The HDI for youth would have been even higher, but for the high level of unemployment among youth, which reduces the estimated income of youth (see the last two rows of table 2.8). The GDI of youth is 0.914, which indicates an even smaller disparity in human development between men and women. HDI in the projections, then, under the same modelling, the HDI would be greater than 0.880 by 2050 and probably generate the potential demographic dividend, pro - vided the recommended policies in educa - tion, the economy and family planning were pursued.\n\n[PDF pages 59-59]\nAlthough the HDI is higher among youth than among the overall population, acceler - ated efforts are needed to apply the nation’s wealth to promote the economic inclusion of youth and improve the living standards of youth. This will be crucial in reaping the benefits of the potential demographic dividend and shaping the sustainable future of"
  },
  {
    "section_id": "chapter_3",
    "title": "The Economic Inclusion of Youth",
    "digest": "[PDF pages 61-66]\nSince independence in 2002 and because of oil revenues over the last 10 years and the strong bipartisan support for conflict prevention, the Government has taken rapid steps towards the goal of making Timor-Leste an upper-middle-income country by 2030. Despite ongoing economic improve - ments and a GDP growth of approximately 4 percent a year in the past five years, Human development by enhancing health, knowledge, skills and awareness increases human capital and broadens opportunities and choices (figure 3.1). Globally, social enterprises constitute a small share of the economy, though they are perceived as an important channel for fulfilling the social de - velopment needs of communities that might otherwise struggle to obtain certain goods or services (Bank 2013). However, this expectation is unrealistic because around 18,000 children leave school every year with skills that are inadequate relative to the needs of the labour market and the new jobs available. While the age at first marriage among people ages up to 19 is 6 percent among married men, the share among married women is significantly higher, at 25 percent (DGE 2015). The expectations of those who have attended secondary school are high, and the idea of employment is strongly linked to work in the public sector (Ostergaard 2005). Education was not available to the majority of the pop - ulation prior to the Indonesian occupation, and Timorese young people recall that, during the occupation, Indonesian teachers used to encourage children to attend school, saying that education would enable them get a government job (Wigglesworth 2016).\n\n[PDF pages 65-70]\nMost of Timor-Leste’s 13 districts have local organizations that offer computer skills training and English classes that are popular because both skills are strongly associated with better chances of obtaining employment. Census data of 2015 show that, among the population, 56 percent of people ages 15–64 were economically active, either working or looking for work in 2015 (DGE 2015; figure 3.2).23 The other 44 percent were inactive, that is, including students, pensioners, and significant numbers of women as home-makers. Moreover, while the share not in education, employment, or training (NEET) among young men peaked at ages 20–24, the peak among young women was at ages 25–29, and the NEET share among young women already exceeded the share in education or work by age 20, indicating significantly reduced opportunities among young women relative to young men. Although youth unemploy - ment rates appeared to drop significantly in both rural and urban areas between 2010 and 2015, the unemployment rate among urban youth, particularly in the 15–24 age group, was still considerable, at 28 percent. Based on a definition of the employed as individuals who worked at least one hour for pay during the week prior to the survey or who worked in unpaid labour for an enter - prise owned by the households in which they live, the NEET measure among young men and women is considered a valuable gauge of how young people are faring in the economy (Curtain 2012). Unemployment Rates, Rural and Urban Youth, 2010 and 2015 (percent) The assessment was conducted before the emergence of a fully functioning formal tech - nical and vocational education and training (TVET) system in Timor-Leste (see chap - ter 4) and thus does not reflect the value of vocational education for employment. Enterprise and Skills Survey, 82 percent of employers reported that first-time job-seekers coming from secondary schools lack job-spe - cific skills and qualifications, while 71 percent stated that youth lack general life and work experience, and 50 percent reported that the major limitations among job-seekers who had received training at technical and vocational schools was low literacy and numeracy skills (SEPFOPE 2014a).\n\n[PDF pages 70-74]\nWork) provided out-of-school men and women ages 16–30 with workforce development training in their rural communities to reduce urban migration. The primary objective was to provide out-of-school men and women ages 16–30 with workforce development training in their rural communities to reduce urban migration. Government and local NGO partners on rural youth, supported a national training initiative on soft skills and entrepreneurship, encouraged employers to hire young workers, linking youth with the regional centres for employment and guidance counselling of the Among under-5-year-olds, 60 percent have experienced significant malnutrition, while stunting affects more than half the population.26 Apart from its clear relevance to food security, the agricultural sector provides a source of income in rural areas and supplies raw materials (from crop surpluses and natural resources) for agroprocessing and agribusiness. A crucial element in this process is the movement of labour from less productive to more productive sectors of the economy (ILO 2016). As in other post-conflict countries, the majority of adults have had little exposure to quality formal education or employment; thus, the culture of business and entrepreneurship needs to be established, a process that takes time and deliberate initiative (Inder and Cornwell 2016). Despite their preferences for office jobs, most youth rely on farming for livelihoods and sources of income; market stalls and pro - duce sales are the major source of work among young people (Curtain 2012). The public sector dominates the economy, providing approximately half of formal employment in 2013 and spending an equivalent of 99 per - cent of non-oil GDP in 2014 (ADB 2016).\n\n[PDF pages 73-77]\nSpecial Zone for Social Market Economy, to reduce poverty in Oecussi-Ambeno and im - prove overall social and economic well-being (UNDP 2017). Local workers are said to account for 70 percent of the construction workforce (10 women out of 220 local employment, nine of which were in domestic roles), but local communities hotly deny this. 28 Local wom - en’s groups have complained that Indonesian women were being brought in to cook for the official launch of the Suai airport project, depriving local women of economic oppor - tunities.29 A community on the land desig - nated for the airport is being relocated. New housing is being built, employing 200 local workers (predominantly men), who are being trained in brickmaking and building skills that they can use in the future, thereby offer - ing new skills to the community. The Government announced in August 2016 that, because the national unemploy - ment rate had reached 11 percent and because few jobs were likely to appear in the private sector in Dili, SEPFOPE would seek oppor - tunities for young people to work overseas.32 Timorese, 5 percent of whom were women, to work in Korea (Wigglesworth and Fonseca 2016). It has enabled almost 1,000 Timorese, 27 percent of whom are women (most ages 26–35), to perform seasonal work for a few months a year since 2012, according to SEPFOPE data. A study of 30 returning workers finds that a lack of business skills and the demands for cash by family members for customary cere - monies are the main constraints on realizing local business investment (Wigglesworth and\n\n[PDF pages 76-80]\nThe influence and involvement of international aid agencies in emergency, rehabilitation and development programmes in the early years of independence (1999–2004) were accompanied by significant growth in civil society, from only 14 local NGOs in 1998 to over 200 registered by the end of 2001 (Wigglesworth 2016). The struggle for independence and of the donor-aid–driven economy during the early years of inde - pendence provided the context in which many civil society activists cultivated a high degree of motivation to achieve social development objectives and realize their commitment to national development (Wigglesworth 2016). The share of employment in the NGO sector is 1.3 percent (DGE 2015). Education has formally adopted a school gardens programme to encourage children to take an interest in food production (Wigglesworth 2016) (box 3.3). NGOs have provided opportunities for skills development for young people in rural areas through training, particularly in infor - mation technology (IT) and English, as well as for jobs by enabling volunteers to learn on-the-job skills. Development Plan 2011–2030 calls for the development of a policy framework to establish co-operatives among the vulnerable to create employment, income and training opportunities. A social enterprise is most effective if it re - flects a combination of an intimate knowledge of and a concern for place with wider, non-local strategic networks to access financing, knowledge and advice (Korsgaard, Ferguson, and Gaddefors 2015). UNDP’s Social Business Project 2012– 2016 aimed to formulate and pilot social business models that can create employment, generate income, enhance livelihoods and produce other positive social impacts in\n\n[PDF pages 80-84]\nThe National Strategic Development Plan 2011–2030 identifies high-value products that could be promoted and produced for niche markets in Timor-Leste. 66 | TIMOR-LESTE NATIONAL HUMAN DEVELOPMENT REPORT 2018 PLANNING THE OPPORTUNITIES FOR A YOUTHFUL POPULATION | 67 3The Economic Inclusion of Youth In March 2017, the Government ap - proved a national tourism policy to provide a clear public framework to ensure growth in • Employment in tourism will reach 15,000 (approximately 4,300 at present). There is a gendered effect in work status because of higher employment and unem - ployment among young men relative to young women. Most economic change is currently taking place in Dili, but more resources need to be concentrated in rural areas to support young people so that they to bring their skills to bear and establish entrepreneurial initiatives in their home environments. Many Timorese youth have work-ready skills through participation in donor-supported work-ready training programmes, migrant work in a more competitive environment overseas where youth have learned new work skills, or the skills and experience they have gained working in civil society organizations in Timor-Leste. 68 | TIMOR-LESTE NATIONAL HUMAN DEVELOPMENT REPORT 2018 PLANNING THE OPPORTUNITIES FOR A YOUTHFUL POPULATION | 69 3The Economic Inclusion of Youth development needs of rural areas.\n\n[PDF pages 84-85]\nIf access to finance can be assured through greater financial literacy, young people would become more well equipped to participate in the solidarity economy and take up enterprise development initiatives. The data presented show that age, education and gender affect the ability of young people to gain employment. Individuals with prima - ry or pre-secondary educational attainment are more likely to be self-employed or working in a household enterprise than to be employed for a wage. A goal of youth is to escape the subsistence lives of 75 percent of Timorese households; so, young people must be supported in helping to transform and develop their environment. One of the ways that young people escape unemployment is to migrate overseas for work. 70 | TIMOR-LESTE NATIONAL HUMAN DEVELOPMENT REPORT 2018 PLANNING THE OPPORTUNITIES FOR A YOUTHFUL POPULATION | 71 3The Economic Inclusion of Youth substantial number of young Timorese in travelling overseas for work to Australia and Korea, and many more have migrated on their own to the United Kingdom. A re - cent survey showed that members of a fifth of all households have migrated overseas for work (IRI 2016). In the National Strategic Development Plan 2011–2030, the Government has identified small enterprises focusing on niche products as an important area of new enterprise devel - opment (Planning Commission 2011)."
  },
  {
    "section_id": "chapter_4",
    "title": "Education and Training in the New Economy",
    "digest": "[PDF pages 87-92]\nJose Araújo, a teacher at Nicolau Lobato Secondary School, teaches Portuguese to 70 students in a classroom. 74 | TIMOR-LESTE NATIONAL HUMAN DEVELOPMENT REPORT 2018 The chapter investigates ways educational initiatives and policies may inspire and motivate young people ages 15–34 or younger to acquire skills and otherwise train and prepare so they may create sustainable livelihoods that will contribute to community needs. These young people, particularly those working within their own communities, can contribute immensely to the transformation of the economy, provide services in rural areas, help put an end to poverty and deprivation and promote health and well-being for all. 74 | TIMOR-LESTE NATIONAL HUMAN DEVELOPMENT REPORT 2018 PLANNING THE OPPORTUNITIES FOR A YOUTHFUL POPULATION | 75 4Education and Training in the New Economy Non-formal education may also become im - portant in Timor-Leste in teaching the sorts of skills not easily leaned in the classroom, an approach supported by the Big 6 youth organizations. The W orld Economic Forum has developed a typology of the 16 skills and qualities of character required by students to deal with the globalized world (figure 4.1). 76 | TIMOR-LESTE NATIONAL HUMAN DEVELOPMENT REPORT 2018 PLANNING THE OPPORTUNITIES FOR A YOUTHFUL POPULATION | 77 4Education and Training in the New Economy literacy and numeracy.\n\n[PDF pages 91-95]\nImproving complementary nonformal education in grades 6–9 Timor-Leste, all students in grades 6–9 (the third cycle of basic education) should be en - couraged to join a complementary non-formal education programme after school at least one day a week. The first two sets of skills, basic skills and generic skills, are needed by everybody and should be available through basic education (up to grade 9) or through adult education among individuals who missed out earlier along their education path. 78 | TIMOR-LESTE NATIONAL HUMAN DEVELOPMENT REPORT 2018 PLANNING THE OPPORTUNITIES FOR A YOUTHFUL POPULATION | 79 4Education and Training in the New Economy their schools. Health and health care initially formed a major part of the girls course, but not the boys course; however, because of requests by communities, the girls and boys courses were combined (Hill 2001). If students do not have computer literacy skills by grade 10, this would be a good time to introduce the subject if the equipment and teachers can be found. Subjects such as bookkeeping, dress-mak - ing, culinary arts, sustainable energy stud - ies, sanitation and health care, carpentry, hospitality services, maritime and fishing services, design and technical drawing, and the introduction to motor mechanics should be available as electives, including practical modules, to all students in grades 10–12 at all high schools. 80 | TIMOR-LESTE NATIONAL HUMAN DEVELOPMENT REPORT 2018 PLANNING THE OPPORTUNITIES FOR A YOUTHFUL POPULATION | 81 4Education and Training in the New Economy\n\n[PDF pages 94-97]\nAustralian certificate 4 in training and assessment was introduced by Victoria University, In many cases, entry into advanced or specialized education establishments can be achieved by demonstrating prior learning, that is, the acquisition of skills and expertise through work or other life experiences rather than through formal education. Curtain (2007) recommends that the experiences of young people in learning by doing be captured on personal skills passports (box 4.3). A programme funded by the United States Agency for International Development to combine work experience positions with training among rural young people in Timor-Leste is applying this concept. 82 | TIMOR-LESTE NATIONAL HUMAN DEVELOPMENT REPORT 2018 Programme (UNDP), the One Laptop per Child non-profit initiative was launched in 2006 to transform education around the world. The initiative’s primary goal continues to be to transform education by enabling children in low-income countries to have access to content, media and computer-programming environments. 82 | TIMOR-LESTE NATIONAL HUMAN DEVELOPMENT REPORT 2018 PLANNING THE OPPORTUNITIES FOR A YOUTHFUL POPULATION | 83 4Education and Training in the New Economy"
  },
  {
    "section_id": "chapter_5",
    "title": "The Fourth Industrial Revolution: Embracing Technology",
    "digest": "[PDF pages 99-104]\n86 | TIMOR-LESTE NATIONAL HUMAN DEVELOPMENT REPORT 2018 The transformation from a dependent economic development model, whereby the means of production are easily replaceable, to a knowledge-based economy requires the adoption of a fresh development strategy, which inevitably depends on access to fund - ing, talent, social capital and an efficient institutional environment. 41 These are also important in involving communities in socially oriented e-commerce, promoting social enterprises, and raising awareness about key government services. 86 | TIMOR-LESTE NATIONAL HUMAN DEVELOPMENT REPORT 2018 PLANNING THE OPPORTUNITIES FOR A YOUTHFUL POPULATION | 87 5The Challenge of the Fourth Industrial Revolution: Embracing Technology Following an analysis of sectoral challenges in ICT, it assesses shared issues associated with technical and voca - tional education and training (TVET) in the Asia and Pacific region and the extent to which TVET in Timor-Leste supports ICTskilled work-ready graduates in the changing world of work. The violence that occurred in the wake of the 1999 referendum resulted in the destruction of the entire telecommunication network and electrical systems (Kalathil 2006; Soares and Mytton 2007; W orld Bank 2013). 88 | TIMOR-LESTE NATIONAL HUMAN DEVELOPMENT REPORT 2018 Age Total Women Men 13–17 20.0 7.0 13.0 18–24 46.0 17.0 29.0 25–34 25.0 8.0 17.0 35–44 5.0 2.0 4.0 45–54 1.5 0.4 1.2 55–64 0.4 0.1 0.3 65+ 1.3 0.3 1.0\n\n[PDF pages 103-107]\nT etum and Portuguese as official languages, which has complicated the introduction of new ICT systems and skills development, especially because trade and education are still largely conducted in Bahasa Indonesian (Das and O’Keefe 2005). Timor-Leste was 134th of 143 countries on the W orld Economic Forum’s 2015 net - worked readiness index (table 5.3). Although e-literacy and a networking capability are critical to social enterprises and innovation in the wider economy, there is only a modest focus on ICT training in tertiary and vocational education in Timor-Leste. Although e-literacy and a networking capability are critical to social enterprises and in - novation in the wider economy, there is only a modest focus on ICT training in tertiary and vocational education in Timor-Leste. Fifth pillar indices Rank, of 143 Value, 1–7 5.01 Quality of educational system 135 2.4 5.02 Quality of mathematics and science education 140 2.1 5.03 Secondary education, gross enrolment ratio, % 114 56.6 5.04 Adult literacy rate, % 100 67.5 Such facilities have been found to produce a substantial positive effect on female participation in the TVET system (Marope, Chakroun, and Holmes 2015). Family-friendly timetabling can also make it easier for women to balance their household, employment and training com - mitments (Marope, Chakroun, and Holmes 2015). College and TVET s in Kiribati and V anuatu have identified targeting strategies to promote wider TVET access among girls and women (ERF 2014).\n\n[PDF pages 107-110]\nNow, people living in remote areas are able to ben - efit from TVET training, which they would have otherwise been unable to participate in because their areas are “only accessible by boat or by walking several hours through bush - land” (DFA T 2012, p. The misalignment of skills with labour mar - ket demands is a significant barrier to the effectiveness of the TVET sector in the Asia and Pacific region, and it is a potential drag on the economy, including social enterprises. The skills that the private, public and social enterprise sectors demand are rapidly evolving, especially in ICT s, but the skills of potential employees are tending to lag (Martinez-Fernandez and Choi 2012). Without assessment, unemployment will continue to coexist alongside job vacancies because of unmet demand for skills (Marope, Chakroun, and Holmes 2015). TVET collaboration with employers and the involvement of employers in the development and delivery of training programmes can help eliminate skills mismatching (Marope, Chakroun, and Holmes 2015). Many youth and adults in the Asia and Pacific region, including Timor-Leste, still lack such skills, often because they have received poor-quality education or education that offers no oppor - tunity to build e-literacy (Marope, Chakroun, and Holmes 2015) (see chapter 4). Evidence in many countries shows that the implementation of these targets, particularly those concerning educational institutions and public access institutions such as libraries, post offices, cultural centres, and so on, where staff can advise and assist the public, can have a huge multiplier effect on the ability of small businesses, including solidarity economy en - terprises, to emerge and prosper (Corredera 2015; ITU and UPU 2010). If the universities had their own research and education networks, they could then give all their students computer literacy classes and train computer systems experts who could the benefit the rest of the education system and the government (Foley 2016).\n\n[PDF pages 110-113]\nSoftware Systems (India), relying on mobile telecommunication, has designed interactive games to disseminate messages on public health care, enterprise development and livelihood generation.49 These games have been developed through long-term, direct engagement with communities and partner organizations. T elecommunication Union has highlighted wider digital opportunities to address youth unemployment (ITU 2014). The trust’s intern programme bridges the digital divide between formal education and the labour force through a two-week training exercise in entrepreneurship and ICT and workforce development, followed by a nine-month internship, after which participants are able to enter the workforce as skilled ICT-focused changemakers.b a: See the website of ICT Watch, Jakarta, Indonesia, at http://ictwatch.id. Globally, increases in mobile technologies are also ex - panding employment opportunities among youth, particularly in the demand for mobile phone–enabled services (Baskaran and Mehta 2016; ITU 2014; Roh 2016). An expanding number of microwork-based organizations are employing people to perform tasks such as labelling photos, describing products, or transcribing scanned documents (ITU 2014). The International Centre for Journalism provided additional training and equipment to the centre, which helped facilitate the social net - working capacity.52 The social network associated with the Suai Media Space has a membership of over 200, and members migrated to a dedicated Facebook site. Founded in 2010, the NGO focuses on (1) promoting local products for local markets, (2) assisting businesses and social enterprises to boost opportunities for vulnerable women, and (3) partnering with public and private organiza - tions to build sustainable businesses. This chapter examines (1) the situation of ICT s in Timor-Leste in the context of the fourth industrial revolution, (2) the role of formal and non-formal training in supporting ICT skills development, and (3) the role of ICT s in supporting social enterprises.\n\n[PDF pages 113-113]\nThe chapter draws out the importance of promoting social inclusion and eliminating the rural-urban divide in accessing training and ICT skills develop - ment opportunities. It is crucial to provide new opportunities for inclusive, innovative, flexible and decentralized forms of employ - ment, knowledge creation and training. The misalignment of skills training and labour market demand is a significant barrier to the development of the ICT sector and social enterprises in Timor-Leste. TVET frequently lacks the technical infrastructure and trained staff necessary to deliver courses that meet the needs of the labour market. Leste national qualifications framework to guarantee the maximum relevance of training. Moreover, in TVET in Timor-Leste, there is only a modest focus on ICT training. Until they do, the provision of ICT skills training and talent development in emerging sectors will remain weak. Promoting decentralized networking for peer communication, knowledge sharing and education can help social enterprises flourish."
  },
  {
    "section_id": "chapter_6",
    "title": "Public Investment in Youth",
    "digest": "[PDF pages 115-119]\nThey believed that the entire liberal notion of economic develop - ment was in crisis (Haq 1973). “Focusing on entitlements—what com - modity bundles a person can command— provides a helpful format for characterizing economic development” , Sen (1983, p. lies in the public policies that were implemented in the framework of the transitional welfare regimes and globalization process” (Defourny and Kim 2011, p. 1) some years earlier, when “clustering and network - ing” were said to be “among the best options to support the growth of SMEs [small and medium enterprises]” , an acknowledged key engine of local employment creation. Timorese men (5.3 years) and women (3.6 years). Furthermore, there is a large disparity between the mean years of schooling among Timorese men (5.3 years) and women (3.6 years) (table 6.2). A significant initiative in health education was launched in 2003, when the country’s leadership took on a health care cooperation pro - gramme with Cuba. In its Skills Outlook 2013, the Organisation for Economic Co-operation and Development (OECD) reinforces the human develop - ment concept that basic education and narrow vocational training are not substitutes for broader, more intensive education.\n\n[PDF pages 119-123]\nA study of 115 countries over 1960–1990 carried out for the W orld Bank showed that, while higher incomes were associated with improvements in mortality rates, the education of women was a much more powerful influence (W ang et al. Institution has published an impressive com - pilation of evidence to support each of the following 10 assertions about the education of girls and women: (1) it increases economic growth and agricultural productivity; (2) improves women’s wages and jobs; (3) saves the lives of children and mothers; (4) leads to smaller, more sustainable families; (5) results in healthier, more well educated children; The late Katarina T omaševski, the United Nations special rapporteur on the right to education, made clear a decade ago that the best way to address gender inequality in education was to remove all forms of school fees, including the costs of school uniforms, books and transport, because “the key to a changed global design of education is an affirmation that education is a public responsibility” (T omaševski 2006, p. Fee-free education, combined with school feeding programmes, to year 12 is the most effective way to address gender in - equality and the schooling deficit. Beyond the poor schooling rates and despite the significant number of prominent, well-educated Timorese women, including the 38.5 percent representation of women among the members of Parliament, as required by a gen - der quota (UNDP 2015), capability develop - ment opportunities among Timorese girls and women are shallow. This should focus on promoting key roles for women in priority cluster development, such as (1) rural livelihoods and food security and (2) health care, community development and ecotourism. Strategy included programmes to enhance nutrition and health care among mothers and girls, improve general food security, promote better hygiene, and increase education in optimal nutrition practice (MOH 2014). 1) to conclude that “GDP [gross domestic product] growth originating in agriculture induces income growth among the 40 percent poorest, which is on the order of three times larger than growth originating in the rest of the economy.” Sustainable rural livelihoods can therefore be a tremendous sink for rural unemployment, while slowing internal migration to the cities.\n\n[PDF pages 122-126]\nMore vigorous investment in additional training, health care education, science and health technology, the development of local medicine, and health care facilities would enable a more pro - foundly cross-linked health sector to emerge that could become a leading feature of the economy of Timor-Leste. Social enterprise programmes could be used as a supplemen - tary approach in health care education, ecot - ourism, or related areas such as disease vector control and environmental management. Almost 95 percent of Timorese youth consider the environment important to livelihoods, but also in culture, history and spiritual matters (chapter 2). Many youth draw a link between unemployment and crime, stating that, if young people have nothing to do, if, for instance, they are not in education, employment, or training (NEET), they may become tempted to carry out socially undesirable activities, such as using drugs or creating conflict. The priorities of the enterprises might include training in farm management, meeting a critical local need, food security, local market develop - ment, ecotourism development, health care promotion, environmental protection, the mobilization of voluntary labour initiatives, or the mobilization of local resources. In the first years after the restoration of independence in 2002, the investment shares of education and health care in the combined state and donor budget declined. The National Strategic Development Plan 2011–2030 expressed the admirable goal of school construction and teacher training to ensure universal secondary school completion through grade 12 by the year 2020 (Planning Nonetheless, in 2015, at 36 percent of the budget, investment in infrastructure was still more than double the combined allocation to education, health care and agriculture (see tables 6.4 and 6.5).\n\n[PDF pages 126-130]\nExperience elsewhere shows that raising school completion rates up to grade 12 can become a major factor in reducing youth unemployment. 114 | TIMOR-LESTE NATIONAL HUMAN DEVELOPMENT REPORT 2018 investment in education, including sub - stantial investment in teacher training, high-quality education facilities and appropriate teacher employment and, in accordance with the 2006 report of the United Nations rapporteur on the right to education, the elimination of all direct or indirect school fees (Planning 3) The ongoing educational deficit and other disadvantages of girls and women in Timor-Leste are damaging children and women’s health, obstructing family planning, hindering infectious disease control and disempowering girls and women. The deficit should be confront - ed through a comprehensive approach aimed at eliminating all school related fees, training and creating employment for a sufficient number of teachers and extending the coverage of school feed - ing programmes into secondary schools through grade 12. 4) In the development of youth training and jobs programmes, the Government should consider seeking to reach the the fourth or fifth level of skills proficiency of the OECD among the population (OECD 2013). 7) One focus of cluster development should be rural livelihoods and food security, drawing on the country’s relative strength in customary land tenure, small farming and the majority of the workforce that is in agriculture, while confronting malnutrition and food insecurity, which are chronic problems. Health care, environmental education and remediation, community organization and critical local infrastructure could be the focus of skills development, social enterprises and employment programmes. T o achieve world class human development and a substantial youth dividend, drawing on interna - tional best practice, the Government should consider allocating 25 percent of the budget to education and training, returning health care spending to at least 12 percent and quadrupling investment in agriculture to at least 8 percent."
  }
]